mdextractor/__init__.py
mdextractor-2025.4.231259.dist-info/licenses/LICENSE
tests/__init__.py
tests/test_mdextractor.py
mdextractor-2025.4.231259.dist-info/METADATA
mdextractor-2025.4.231259.dist-info/WHEEL
mdextractor-2025.4.231259.dist-info/top_level.txt
mdextractor-2025.4.231259.dist-info/RECORD
