Metadata-Version: 2.4
Name: mdextractor
Version: 2025.4.231259
Summary: Extract Markdown code blocks from text strings.
Home-page: https://github.com/chigwell/mdextractor
Author: Eugene Evstafev
Author-email: chigwel@gmail.com
License: MIT
Classifier: License :: OSI Approved :: MIT License
Classifier: Development Status :: 3 - Alpha
Classifier: Intended Audience :: Developers
Classifier: Programming Language :: Python :: 3
Classifier: Operating System :: OS Independent
Requires-Python: >=3.6
License-File: LICENSE
Dynamic: author
Dynamic: author-email
Dynamic: classifier
Dynamic: description
Dynamic: description-content-type
Dynamic: home-page
Dynamic: license
Dynamic: license-file
Dynamic: requires-python
Dynamic: summary
